examples/__init__.py
examples/a_generate_phantoms_for_examples.py
examples/caliber_usage_distances_example.py
examples/caliber_usage_example.py
examples/manipulator_example.py
examples/prototype_check_imperfections.py
examples/prototype_clean_a_segmentation.py
examples/prototype_open_segmentations_in_freeview.py
examples/prototype_segment_an_image.py
examples/prototype_symmetrise_a_segmentation.py
examples/simple_label_fusion.py
examples/simple_relabelling_example.py
nilabels/__init__.py
nilabels/definitions.py
nilabels/agents/__init__.py
nilabels/agents/agents_controller.py
nilabels/agents/checker.py
nilabels/agents/fuser.py
nilabels/agents/header_controller.py
nilabels/agents/intensities_manipulator.py
nilabels/agents/labels_manipulator.py
nilabels/agents/math.py
nilabels/agents/measurer.py
nilabels/agents/segmenter.py
nilabels/agents/shape_manipulator.py
nilabels/agents/symmetrizer.py
nilabels/tools/__init__.py
nilabels/tools/aux_methods/__init__.py
nilabels/tools/aux_methods/label_descriptor_manager.py
nilabels/tools/aux_methods/morpological_operations.py
nilabels/tools/aux_methods/sanity_checks.py
nilabels/tools/aux_methods/utils.py
nilabels/tools/aux_methods/utils_nib.py
nilabels/tools/aux_methods/utils_path.py
nilabels/tools/aux_methods/utils_rotations.py
nilabels/tools/caliber/__init__.py
nilabels/tools/caliber/distances.py
nilabels/tools/caliber/volumes_and_values.py
nilabels/tools/cleaning/__init__.py
nilabels/tools/cleaning/labels_cleaner.py
nilabels/tools/detections/__init__.py
nilabels/tools/detections/check_imperfections.py
nilabels/tools/detections/contours.py
nilabels/tools/detections/get_segmentation.py
nilabels/tools/detections/island_detection.py
nilabels/tools/image_colors_manipulations/__init__.py
nilabels/tools/image_colors_manipulations/cutter.py
nilabels/tools/image_colors_manipulations/normaliser.py
nilabels/tools/image_colors_manipulations/relabeller.py
nilabels/tools/image_colors_manipulations/segmentation_to_rgb.py
nilabels-0.0.8.dist-info/LICENCE.txt
nilabels-0.0.8.dist-info/METADATA
nilabels-0.0.8.dist-info/WHEEL
nilabels-0.0.8.dist-info/top_level.txt
nilabels-0.0.8.dist-info/RECORD
