Metadata-Version: 2.1
Name: nilabels
Version: 0.0.8
Summary: Toolkit to manipulate and measure image segmentations in nifti format.
Home-page: https://github.com/nipy/nilabels
Author: sebastiano ferraris
Author-email: sebastiano.ferraris@gmail.com
License: MIT
Platform: UNKNOWN
Requires-Dist: matplotlib
Requires-Dist: nibabel (>=2.3.3)
Requires-Dist: numpy (>=1.16.0)
Requires-Dist: pandas (>=0.23.4)
Requires-Dist: pytest (>=4.1.1)
Requires-Dist: scipy (>=1.2.0)
Requires-Dist: setuptools (>=40.6.3)
Requires-Dist: scikit-image (>=0.14.2)
Requires-Dist: sympy (>=1.3)
Requires-Dist: tabulate (>=0.8.2)
Requires-Dist: scikit-learn (>=0.20.2)
